.editorconfig
.gitignore
.travis.yml
AUTHORS.rst
CONTRIBUTING.rst
HISTORY.rst
LICENSE
MANIFEST.in
Makefile
README.rst
requirements.txt
setup.cfg
setup.py
tail
tox.ini
docs/Makefile
docs/authors.rst
docs/conf.py
docs/contributing.rst
docs/history.rst
docs/index.rst
docs/installation.rst
docs/make.bat
docs/readme.rst
docs/usage.rst
jsail/__init__.py
jsail/cmd.py
jsail.egg-info/PKG-INFO
jsail.egg-info/SOURCES.txt
jsail.egg-info/dependency_links.txt
jsail.egg-info/entry_points.txt
jsail.egg-info/not-zip-safe
jsail.egg-info/requires.txt
jsail.egg-info/top_level.txt
tests/__init__.py
tests/test_jsail.py