Metadata-Version: 1.1
Name: jsail
Version: 0.3.0
Summary: A tail for JSON logs.
Home-page: https://github.com/svetlyak40wt/jsail
Author: Alexander Artemenko
Author-email: svetlyak.40wt@gmail.com
License: BSD
Keywords: jsail
Platform: UNKNOWN
Classifier: Development Status :: 2 - Pre-Alpha
Classifier: Intended Audience :: Developers
Classifier: License :: OSI Approved :: BSD License
Classifier: Natural Language :: English
Classifier: Programming Language :: Python :: 2
Classifier: Programming Language :: Python :: 2.6
Classifier: Programming Language :: Python :: 2.7
Classifier: Programming Language :: Python :: 3
Classifier: Programming Language :: Python :: 3.3
Classifier: Programming Language :: Python :: 3.4
